llama_index/embeddings/openvino_genai/__init__.py
llama_index/embeddings/openvino_genai/base.py
llama_index_embeddings_openvino_genai-0.6.1.dist-info/METADATA
llama_index_embeddings_openvino_genai-0.6.1.dist-info/WHEEL
llama_index_embeddings_openvino_genai-0.6.1.dist-info/licenses/LICENSE
llama_index_embeddings_openvino_genai-0.6.1.dist-info/RECORD
