Metadata-Version: 2.4
Name: llama-index-embeddings-openvino-genai
Version: 0.6.1
Summary: llama-index embeddings openvino genai integration
Author-email: Your Name <you@example.com>
License-Expression: MIT
License-File: LICENSE
Requires-Python: <4.0,>=3.9
Requires-Dist: llama-index-core<0.15,>=0.13.0
Requires-Dist: openvino-genai>=2025.1.0.0
Requires-Dist: openvino-tokenizers>=2025.1.0.0
Requires-Dist: openvino>=2025.1.0
